.VERSION
AUTHORS.rst
CONTRIBUTING.rst
HISTORY.rst
LICENSE
MANIFEST.in
Pipfile
Pipfile.lock
README.rst
USAGE.rst
dev-requirements.txt
requirements.txt
setup.cfg
setup.py
docs/Makefile
docs/authors.rst
docs/conf.py
docs/contributing.rst
docs/history.rst
docs/index.rst
docs/installation.rst
docs/readme.rst
docs/usage.rst
tests/test_wikiseriesricardolib.py
wikiseriesricardolib/.VERSION
wikiseriesricardolib/AUTHORS.rst
wikiseriesricardolib/CONTRIBUTING.rst
wikiseriesricardolib/HISTORY.rst
wikiseriesricardolib/LICENSE
wikiseriesricardolib/Pipfile
wikiseriesricardolib/Pipfile.lock
wikiseriesricardolib/README.rst
wikiseriesricardolib/USAGE.rst
wikiseriesricardolib/__init__.py
wikiseriesricardolib/_version.py
wikiseriesricardolib/dev-requirements.txt
wikiseriesricardolib/requirements.txt
wikiseriesricardolib/wikiseriesricardolib.py
wikiseriesricardolib/wikiseriesricardolibexceptions.py
wikiseriesricardolib.egg-info/PKG-INFO
wikiseriesricardolib.egg-info/SOURCES.txt
wikiseriesricardolib.egg-info/dependency_links.txt
wikiseriesricardolib.egg-info/not-zip-safe
wikiseriesricardolib.egg-info/requires.txt
wikiseriesricardolib.egg-info/top_level.txt