Metadata-Version: 2.1
Name: wikiseriesricardolib
Version: 0.1.0
Summary: Library to use wikipedia to query tv series episode lists.
Home-page: https://github.com/rjacobs90/wikiseriesricardolib
Author: Ricardo Jacobs
Author-email: ricardojacobs20@gmail.com
License: MIT
Keywords: wikiseriesricardolib wikipedia tv-series
Classifier: Development Status :: 3 - Alpha
Classifier: Intended Audience :: Developers
Classifier: License :: OSI Approved :: MIT License
Classifier: Natural Language :: English
Classifier: Programming Language :: Python :: 3.9
License-File: LICENSE
License-File: AUTHORS.rst
